transcribe_everything/__init__.py
transcribe_everything/args.py
transcribe_everything/batch.py
transcribe_everything/cli.py
transcribe_everything/cli_docker.py
transcribe_everything/cli_init.py
transcribe_everything/constants.py
transcribe_everything/lang.py
transcribe_everything/run.py
transcribe_everything/tmpdir.py
transcribe_everything/transcription_pipeline.py
transcribe_everything/util.py
transcribe_everything/assets/sample.mp3
transcribe_everything-1.5.39.dist-info/licenses/LICENSE
transcribe_everything-1.5.39.dist-info/METADATA
transcribe_everything-1.5.39.dist-info/WHEEL
transcribe_everything-1.5.39.dist-info/entry_points.txt
transcribe_everything-1.5.39.dist-info/top_level.txt
transcribe_everything-1.5.39.dist-info/RECORD
