Metadata-Version: 2.4
Name: transcribe_everything
Version: 1.5.39
Summary: transcribe transcriptions ai whisper
Home-page: https://github.com/zackees/transcribe-everything
Maintainer: Zachary Vorhies
License: BSD 3-Clause License
Keywords: ai,transcribe,anything,everything,s3,remote,big,data
Classifier: Programming Language :: Python :: 3
Requires-Python: >=3.10
License-File: LICENSE
Requires-Dist: langdetect>=1.0.9
Requires-Dist: transcribe-anything>=3.0.7
Requires-Dist: virtual-fs>=1.0.23
Dynamic: home-page
Dynamic: license-file
Dynamic: maintainer
